{
  "project_info": {
    "project_number": "305435743322",
    "project_id": "myencryptapp-c509c",
    "storage_bucket": "myencryptapp-c509c.appspot.com"
  },
  "client": [
    {
      "client_info": {
        "mobilesdk_app_id": "1:305435743322:android:c050514ead7f61a242b463",
        "android_client_info": {
          "package_name": "com.example.myencryptapp"
        }
      },
      "oauth_client": [],
      "api_key": [
        {
          "current_key": "AIzaSyBkYF-aM761VUpsunwB_bQaWq70_sx_zrA"
        }
      ],
      "services": {
        "appinvite_service": {
          "other_platform_oauth_client": []
        }
      }
    },
    {
      "client_info": {
        "mobilesdk_app_id": "1:305435743322:android:2c9091e0772112c342b463",
        "android_client_info": {
          "package_name": "com.example.mypersadacinta"
        }
      },
      "oauth_client": [],
      "api_key": [
        {
          "current_key": "AIzaSyBkYF-aM761VUpsunwB_bQaWq70_sx_zrA"
        }
      ],
      "services": {
        "appinvite_service": {
          "other_platform_oauth_client": []
        }
      }
    }
  ],
  "configuration_version": "1"
}